<annotation>
	<folder>JPEGImages</folder>
	<filename>vlcsnap-2024-08-06-14h04m48s871.jpg</filename>
	<path>C:\Users\13905\AutoLabelImg\0802_11labels04\images\train</path>
	<source>
		<database>Unknown</database>
	</source>
	<size>
		<width>1980</width>
		<height>1020</height>
		<depth>3</depth>
	</size>
	<segmented>0</segmented>
	<object>
		<name>bus</name>
		<pose>Unspecified</pose>
		<truncated>0</truncated>
		<difficult>0</difficult>
		<bndbox>
			<xmin>1389</xmin>
			<ymin>368</ymin>
			<xmax>1920</xmax>
			<ymax>1076</ymax>
		</bndbox>
	</object>
<object>
		<name>bus</name>
		<pose>Unspecified</pose>
		<truncated>0</truncated>
		<difficult>0</difficult>
		<bndbox>
			<xmin>661</xmin>
			<ymin>338</ymin>
			<xmax>1398</xmax>
			<ymax>1077</ymax>
		</bndbox>
	</object>
<object>
		<name>car</name>
		<pose>Unspecified</pose>
		<truncated>0</truncated>
		<difficult>0</difficult>
		<bndbox>
			<xmin>493</xmin>
			<ymin>807</ymin>
			<xmax>658</xmax>
			<ymax>965</ymax>
		</bndbox>
	</object>
<object>
		<name>car</name>
		<pose>Unspecified</pose>
		<truncated>0</truncated>
		<difficult>0</difficult>
		<bndbox>
			<xmin>173</xmin>
			<ymin>796</ymin>
			<xmax>555</xmax>
			<ymax>1074</ymax>
		</bndbox>
	</object>
<object>
		<name>car</name>
		<pose>Unspecified</pose>
		<truncated>0</truncated>
		<difficult>0</difficult>
		<bndbox>
			<xmin>145</xmin>
			<ymin>761</ymin>
			<xmax>295</xmax>
			<ymax>878</ymax>
		</bndbox>
	</object>
<object>
		<name>traffic light</name>
		<pose>Unspecified</pose>
		<truncated>0</truncated>
		<difficult>0</difficult>
		<bndbox>
			<xmin>1163</xmin>
			<ymin>247</ymin>
			<xmax>1235</xmax>
			<ymax>348</ymax>
		</bndbox>
	</object>
<object>
		<name>traffic light</name>
		<pose>Unspecified</pose>
		<truncated>0</truncated>
		<difficult>0</difficult>
		<bndbox>
			<xmin>303</xmin>
			<ymin>589</ymin>
			<xmax>330</xmax>
			<ymax>649</ymax>
		</bndbox>
	</object>
<object>
		<name>traffic light</name>
		<pose>Unspecified</pose>
		<truncated>0</truncated>
		<difficult>0</difficult>
		<bndbox>
			<xmin>1016</xmin>
			<ymin>253</ymin>
			<xmax>1084</xmax>
			<ymax>345</ymax>
		</bndbox>
	</object>
<object>
		<name>person</name>
		<pose>Unspecified</pose>
		<truncated>0</truncated>
		<difficult>0</difficult>
		<bndbox>
			<xmin>574</xmin>
			<ymin>741</ymin>
			<xmax>635</xmax>
			<ymax>811</ymax>
		</bndbox>
	</object>
<object>
		<name>traffic light</name>
		<pose>Unspecified</pose>
		<truncated>0</truncated>
		<difficult>0</difficult>
		<bndbox>
			<xmin>348</xmin>
			<ymin>590</ymin>
			<xmax>381</xmax>
			<ymax>654</ymax>
		</bndbox>
	</object>
<object>
		<name>car</name>
		<pose>Unspecified</pose>
		<truncated>0</truncated>
		<difficult>0</difficult>
		<bndbox>
			<xmin>382</xmin>
			<ymin>738</ymin>
			<xmax>566</xmax>
			<ymax>833</ymax>
		</bndbox>
	</object>
</annotation>