<annotation>
	<folder>JPEGImages</folder>
	<filename>vlcsnap-2024-08-07-09h32m22s165.jpg</filename>
	<path>C:\Users\13905\AutoLabelImg\0802_11labels04\images\train</path>
	<source>
		<database>Unknown</database>
	</source>
	<size>
		<width>1980</width>
		<height>1020</height>
		<depth>3</depth>
	</size>
	<segmented>0</segmented>
	<object>
		<name>traffic light</name>
		<pose>Unspecified</pose>
		<truncated>0</truncated>
		<difficult>0</difficult>
		<bndbox>
			<xmin>876</xmin>
			<ymin>591</ymin>
			<xmax>888</xmax>
			<ymax>622</ymax>
		</bndbox>
	</object>
</annotation>