<annotation>
	<folder>JPEGImages</folder>
	<filename>vlcsnap-2024-08-07-09h33m38s794.jpg</filename>
	<path>C:\Users\13905\AutoLabelImg\0802_11labels04\images\train</path>
	<source>
		<database>Unknown</database>
	</source>
	<size>
		<width>1980</width>
		<height>1020</height>
		<depth>3</depth>
	</size>
	<segmented>0</segmented>
	<object>
		<name>hdv</name>
		<pose>Unspecified</pose>
		<truncated>0</truncated>
		<difficult>0</difficult>
		<bndbox>
			<xmin>654</xmin>
			<ymin>660</ymin>
			<xmax>942</xmax>
			<ymax>975</ymax>
		</bndbox>
	</object>
<object>
		<name>car</name>
		<pose>Unspecified</pose>
		<truncated>0</truncated>
		<difficult>0</difficult>
		<bndbox>
			<xmin>1069</xmin>
			<ymin>816</ymin>
			<xmax>1238</xmax>
			<ymax>953</ymax>
		</bndbox>
	</object>
<object>
		<name>hdv</name>
		<pose>Unspecified</pose>
		<truncated>0</truncated>
		<difficult>0</difficult>
		<bndbox>
			<xmin>1100</xmin>
			<ymin>619</ymin>
			<xmax>1308</xmax>
			<ymax>910</ymax>
		</bndbox>
	</object>
<object>
		<name>red</name>
		<pose>Unspecified</pose>
		<truncated>0</truncated>
		<difficult>0</difficult>
		<bndbox>
			<xmin>1371</xmin>
			<ymin>636</ymin>
			<xmax>1384</xmax>
			<ymax>671</ymax>
		</bndbox>
	</object>
<object>
		<name>red</name>
		<pose>Unspecified</pose>
		<truncated>0</truncated>
		<difficult>0</difficult>
		<bndbox>
			<xmin>1337</xmin>
			<ymin>637</ymin>
			<xmax>1350</xmax>
			<ymax>671</ymax>
		</bndbox>
	</object>
<object>
		<name>car</name>
		<pose>Unspecified</pose>
		<truncated>0</truncated>
		<difficult>0</difficult>
		<bndbox>
			<xmin>1305</xmin>
			<ymin>777</ymin>
			<xmax>1353</xmax>
			<ymax>866</ymax>
		</bndbox>
	</object>
<object>
		<name>green</name>
		<pose>Unspecified</pose>
		<truncated>0</truncated>
		<difficult>0</difficult>
		<bndbox>
			<xmin>1498</xmin>
			<ymin>669</ymin>
			<xmax>1511</xmax>
			<ymax>704</ymax>
		</bndbox>
	</object>
<object>
		<name>car</name>
		<pose>Unspecified</pose>
		<truncated>0</truncated>
		<difficult>0</difficult>
		<bndbox>
			<xmin>1061</xmin>
			<ymin>799</ymin>
			<xmax>1103</xmax>
			<ymax>877</ymax>
		</bndbox>
	</object>
</annotation>