<annotation>
	<folder>JPEGImages</folder>
	<filename>vlcsnap-2024-08-07-09h32m01s926.jpg</filename>
	<path>C:\Users\13905\AutoLabelImg\0802_11labels04\images\train</path>
	<source>
		<database>Unknown</database>
	</source>
	<size>
		<width>1980</width>
		<height>1020</height>
		<depth>3</depth>
	</size>
	<segmented>0</segmented>
	<object>
		<name>car</name>
		<pose>Unspecified</pose>
		<truncated>0</truncated>
		<difficult>0</difficult>
		<bndbox>
			<xmin>965</xmin>
			<ymin>808</ymin>
			<xmax>1023</xmax>
			<ymax>860</ymax>
		</bndbox>
	</object>
<object>
		<name>red</name>
		<pose>Unspecified</pose>
		<truncated>0</truncated>
		<difficult>0</difficult>
		<bndbox>
			<xmin>818</xmin>
			<ymin>717</ymin>
			<xmax>828</xmax>
			<ymax>742</ymax>
		</bndbox>
	</object>
<object>
		<name>red</name>
		<pose>Unspecified</pose>
		<truncated>0</truncated>
		<difficult>0</difficult>
		<bndbox>
			<xmin>1070</xmin>
			<ymin>718</ymin>
			<xmax>1078</xmax>
			<ymax>740</ymax>
		</bndbox>
	</object>
<object>
		<name>car</name>
		<pose>Unspecified</pose>
		<truncated>0</truncated>
		<difficult>0</difficult>
		<bndbox>
			<xmin>904</xmin>
			<ymin>815</ymin>
			<xmax>940</xmax>
			<ymax>844</ymax>
		</bndbox>
	</object>
<object>
		<name>hdv</name>
		<pose>Unspecified</pose>
		<truncated>0</truncated>
		<difficult>0</difficult>
		<bndbox>
			<xmin>856</xmin>
			<ymin>787</ymin>
			<xmax>901</xmax>
			<ymax>836</ymax>
		</bndbox>
	</object>
<object>
		<name>car</name>
		<pose>Unspecified</pose>
		<truncated>0</truncated>
		<difficult>0</difficult>
		<bndbox>
			<xmin>832</xmin>
			<ymin>811</ymin>
			<xmax>873</xmax>
			<ymax>845</ymax>
		</bndbox>
	</object>
<object>
		<name>cycle</name>
		<pose>Unspecified</pose>
		<truncated>0</truncated>
		<difficult>0</difficult>
		<bndbox>
			<xmin>1155</xmin>
			<ymin>808</ymin>
			<xmax>1170</xmax>
			<ymax>835</ymax>
		</bndbox>
	</object>
</annotation>